modo/__init__.py
modo/example.py
modo/services/__init__.py
modo/utils/__init__.py
modo/utils/s3.py
modo-0.0.15.dist-info/LICENSE
modo-0.0.15.dist-info/METADATA
modo-0.0.15.dist-info/WHEEL
modo-0.0.15.dist-info/entry_points.txt
modo-0.0.15.dist-info/top_level.txt
modo-0.0.15.dist-info/RECORD
