Metadata-Version: 2.1
Name: modo
Version: 0.0.15
Summary: Bootstrap Framework for immutable machines
Home-page: https://github.com/pypa/sampleproject
Author: Stefan Schweer
Author-email: s.schweer@heavycloud.de
License: MIT
Keywords: bootstrap
Platform: UNKNOWN
Classifier: Development Status :: 3 - Alpha
Classifier: Intended Audience :: System Administrators
Classifier: Topic :: System :: Installation/Setup
Classifier: License :: OSI Approved :: MIT License
Classifier: Programming Language :: Python :: 3.6
Classifier: Programming Language :: Python :: 3.7
Requires-Dist: click
Requires-Dist: boto3
Requires-Dist: jinja2
Requires-Dist: pyaml
Requires-Dist: watchtower
Provides-Extra: dev
Requires-Dist: twine; extra == 'dev'
Requires-Dist: wheel; extra == 'dev'
Requires-Dist: pylint; extra == 'dev'
Requires-Dist: pytest; extra == 'dev'
Requires-Dist: pytest-mock; extra == 'dev'
Requires-Dist: sphinx; extra == 'dev'
Requires-Dist: sphinx-bootstrap-theme; extra == 'dev'
Requires-Dist: sphinx-autodoc-annotation; extra == 'dev'
